[
  {
    "name": "active-status",
    "providerId": "user-attribute-ldap-mapper",
    "providerType": "org.keycloak.storage.ldap.mappers.LDAPStorageMapper",
    "config": {
        "ldap.attribute": [
            "inetUserStatus"
        ],
        "attribute.force.default": [
            "true"
        ],
        "is.mandatory.in.ldap": [
            "true"
        ],
        "is.binary.attribute": [
            "false"
        ],
        "read.only": [
            "false"
        ],
        "always.read.value.from.ldap": [
            "false"
        ],
        "user.model.attribute": [
            "inetUserStatus"
        ]
    }
},{
    "name": "common-name",
    "providerId": "user-attribute-ldap-mapper",
    "providerType": "org.keycloak.storage.ldap.mappers.LDAPStorageMapper",
    "config": {
        "ldap.attribute": [
            "cn"
        ],
        "is.mandatory.in.ldap": [
            "true"
        ],
        "attribute.force.default": [
            "false"
        ],
        "is.binary.attribute": [
            "false"
        ],
        "always.read.value.from.ldap": [
            "false"
        ],
        "read.only": [
            "false"
        ],
        "user.model.attribute": [
            "username"
        ]
    }
},
  {
    "name": "interim-ad-username",
    "providerId": "user-attribute-ldap-mapper",
    "providerType": "org.keycloak.storage.ldap.mappers.LDAPStorageMapper",
    "config": {
        "ldap.attribute": [
            "interimADUsername"
        ],
        "attribute.force.default": [
            "false"
        ],
        "is.mandatory.in.ldap": [
            "false"
        ],
        "is.binary.attribute": [
            "false"
        ],
        "read.only": [
            "false"
        ],
        "always.read.value.from.ldap": [
            "false"
        ],
        "user.model.attribute": [
            "interimADUsername"
        ]
    }
},
{
    "name": "preferred-lang",
    "providerId": "user-attribute-ldap-mapper",
    "providerType": "org.keycloak.storage.ldap.mappers.LDAPStorageMapper",
    "config": {
        "ldap.attribute": [
            "preferredLanguage"
        ],
        "attribute.default.value": [
            "fr"
        ],
        "attribute.force.default": [
            "true"
        ],
        "is.mandatory.in.ldap": [
            "true"
        ],
        "is.binary.attribute": [
            "false"
        ],
        "always.read.value.from.ldap": [
            "false"
        ],
        "read.only": [
            "false"
        ],
        "user.model.attribute": [
            "preferredLanguage"
        ]
    }
},
{
    "name": "preferred-locale",
    "providerId": "user-attribute-ldap-mapper",
    "providerType": "org.keycloak.storage.ldap.mappers.LDAPStorageMapper",
    "config": {
        "ldap.attribute": [
            "preferredLocale"
        ],
        "is.mandatory.in.ldap": [
            "true"
        ],
        "attribute.force.default": [
            "true"
        ],
        "is.binary.attribute": [
            "false"
        ],
        "always.read.value.from.ldap": [
            "false"
        ],
        "read.only": [
            "false"
        ],
        "user.model.attribute": [
            "preferredLocale"
        ]
    }
},
{
    "name": "referenced-ad-username",
    "providerId": "user-attribute-ldap-mapper",
    "providerType": "org.keycloak.storage.ldap.mappers.LDAPStorageMapper",
    "config": {
        "ldap.attribute": [
            "referencedADUsername"
        ],
        "is.mandatory.in.ldap": [
            "false"
        ],
        "attribute.force.default": [
            "false"
        ],
        "is.binary.attribute": [
            "false"
        ],
        "read.only": [
            "false"
        ],
        "always.read.value.from.ldap": [
            "false"
        ],
        "user.model.attribute": [
            "referencedADUsername"
        ]
    }
},
  {
    "name": "group",
    "providerId": "group-ldap-mapper",
    "providerType": "org.keycloak.storage.ldap.mappers.LDAPStorageMapper",
    "config": {
        "membership.attribute.type": [
            "DN"
        ],
        "group.name.ldap.attribute": [
            "cn"
        ],
        "membership.user.ldap.attribute": [
            "sAMAccountName"
        ],
        "preserve.group.inheritance": [
            "false"
        ],
        "groups.dn": [
            "ou=groups,ou=identities"
        ],
        "mapped.group.attributes": [
            "uniqueMember"
        ],
        "mode": [
            "LDAP_ONLY"
        ],
        "user.roles.retrieve.strategy": [
            "LOAD_GROUPS_BY_MEMBER_ATTRIBUTE"
        ],
        "ignore.missing.groups": [
            "false"
        ],
        "membership.ldap.attribute": [
            "uniqueMember"
        ],
        "group.object.classes": [
            "groupOfUniqueNames"
        ],
        "memberof.ldap.attribute": [
            "memberOf"
        ],
        "drop.non.existing.groups.during.sync": [
            "false"
        ],
        "groups.path": [
            "/"
        ]
    }
}
]
